[{"NombreProyecto":"ACP - Coursetune","NombreLider":"Castro Estrada, Alberto"},{"NombreProyecto":"ACP - Migracion a WordPress","NombreLider":"Ivan Flores"},{"NombreProyecto":"ARF - Maintenance","NombreLider":"Rodrigo Reyes"},{"NombreProyecto":"ARF - Performance Testing","NombreLider":"Rodrigo Reyes"},{"NombreProyecto":"AUB - DCS-Poopnet","NombreLider":"Jose Cortes"},{"NombreProyecto":"AUB - Direct Mail","NombreLider":"Jose Cortes"},{"NombreProyecto":"AUB - LMPBP (Local Marketing Plan Budget Platform)","NombreLider":"Jose Cortes"},{"NombreProyecto":"AUB - Swimming Pool","NombreLider":"Raul Aguilera"},{"NombreProyecto":"BRA - Kepler","NombreLider":"Emmanuel Chavez"},{"NombreProyecto":"BRA - Kepler","NombreLider":"Francisco Leyva"},{"NombreProyecto":"BRA - Kepler","NombreLider":"Gerardo Gonzalez"},{"NombreProyecto":"BRA - PM tools modernization implementation","NombreLider":"Alcocer Torres, Jorge Guadalupe"},{"NombreProyecto":"BRA - PM tools modernization implementation","NombreLider":"Anabel Ruiz"},{"NombreProyecto":"BRA - PM tools modernization implementation","NombreLider":"Balderas Medina, Gerardo Alberto"},{"NombreProyecto":"BRA - PM tools modernization implementation","NombreLider":"Campos Martinez, Ricardo Ismael"},{"NombreProyecto":"BRA - PM tools modernization implementation","NombreLider":"Carrillo Martinez, Lilliann"},{"NombreProyecto":"BRA - PM tools modernization implementation","NombreLider":"Eduardo Muñoz"},{"NombreProyecto":"BRA - PM tools modernization implementation","NombreLider":"Irasema Fernandez"},{"NombreProyecto":"BRA - PM tools modernization implementation","NombreLider":"Jorge Escamilla"},{"NombreProyecto":"BRA - PM tools modernization implementation","NombreLider":"Leonor Miranda"},{"NombreProyecto":"BRA - PM tools modernization implementation","NombreLider":"Luis Quintero"},{"NombreProyecto":"BRA - PM tools modernization implementation","NombreLider":"Santoyo Miranda, Alfredo"},{"NombreProyecto":"BRA - Snowflake Data Migration","NombreLider":"Gonzalez Camargo, Jaime Alan"},{"NombreProyecto":"BRA - Snowflake Data Migration","NombreLider":"Guillermo Cantu"},{"NombreProyecto":"BRA - Snowflake Data Migration","NombreLider":"Isaac Larraguibel"},{"NombreProyecto":"BRA - Snowflake Data Migration","NombreLider":"Luis Quintero"},{"NombreProyecto":"BRA - Snowflake Data Migration","NombreLider":"Saldaña Lan, Monica Margarita"},{"NombreProyecto":"BRA - Support Kepler-BSecure","NombreLider":"Ricardo Ramirez"},{"NombreProyecto":"DOD - Middle Back Office","NombreLider":"Leonor Miranda"},{"NombreProyecto":"EPE - Pruebas de Regresion","NombreLider":"Atzin Zuniga"},{"NombreProyecto":"EET - Atlas","NombreLider":"Osvaldo De la Garza"},{"NombreProyecto":"FSX - FSIL UX","NombreLider":"García Lara, Carlos Abraham"},{"NombreProyecto":"FSX - FSIL UX","NombreLider":"Hernandez Morales, Jose"},{"NombreProyecto":"FSX - FSX JSI","NombreLider":"Galindo Gamboa, Luz Elena"},{"NombreProyecto":"FSX - FSX JSI","NombreLider":"Hernandez Morales, Jose"},{"NombreProyecto":"FSX - FSX Pacer Pro","NombreLider":"Hernandez Morales, Jose"},{"NombreProyecto":"FSX - FSX Security Patch","NombreLider":"Galindo Gamboa, Luz Elena"},{"NombreProyecto":"FSX - FSX Security Patch","NombreLider":"García Lara, Carlos Abraham"},{"NombreProyecto":"FSX - FSX Security Patch","NombreLider":"Hernandez Morales, Jose"},{"NombreProyecto":"FSX - FSX-FSIL Filing Integration","NombreLider":"Hernandez Morales, Jose"},{"NombreProyecto":"FSX - Maintenance","NombreLider":"Alejandro Garcia"},{"NombreProyecto":"FSX - Maintenance","NombreLider":"Galindo Gamboa, Luz Elena"},{"NombreProyecto":"FSX - Maintenance","NombreLider":"García Lara, Carlos Abraham"},{"NombreProyecto":"FSX - Maintenance","NombreLider":"Hernandez Morales, Jose"},{"NombreProyecto":"FSX - NFE JTI","NombreLider":"Alejandro Garcia"},{"NombreProyecto":"FSX - Security Incident 2021-11 Response Audit","NombreLider":"Rodrigo Reyes"},{"NombreProyecto":"FSX - Tyler Platform","NombreLider":"Galindo Gamboa, Luz Elena"},{"NombreProyecto":"FSX - Tyler Platform","NombreLider":"García Lara, Carlos Abraham"},{"NombreProyecto":"IPS -  Process & Cumplimiento","NombreLider":"Lyzett Uribe"},{"NombreProyecto":"IPS - Administration & Finance","NombreLider":"Rosa Trevino"},{"NombreProyecto":"IPS - Central","NombreLider":"Hadwin Zaragoza"},{"NombreProyecto":"IPS - Chronos","NombreLider":"Guillermo Cantu"},{"NombreProyecto":"IPS - Chronos Mobile","NombreLider":"Guillermo Cantu"},{"NombreProyecto":"IPS - Cierre de Evaluacion","NombreLider":"Eduardo Muñoz"},{"NombreProyecto":"IPS - Human Resources","NombreLider":"Alejandra Esquivel"},{"NombreProyecto":"IPS - Information Technology","NombreLider":"Alberto Raya"},{"NombreProyecto":"IPS - Recon","NombreLider":"NA"},{"NombreProyecto":"IPS - Talent Acquisition","NombreLider":"Karla Ibarra"},{"NombreProyecto":"IPS - Talent fullfilment","NombreLider":"Lazaro Salinas"},{"NombreProyecto":"IPS - University Reloaded","NombreLider":"NA"},{"NombreProyecto":"IRV -  Office - Heroku","NombreLider":"Guillermo Cantu"},{"NombreProyecto":"IRV - Accounts","NombreLider":"Guillermo Cantu"},{"NombreProyecto":"IRV - Accounts","NombreLider":"IRV -  Office - Heroku"},{"NombreProyecto":"IRV - Appartments QA","NombreLider":"Fernando Cortes"},{"NombreProyecto":"IRV - Office QA","NombreLider":"Aaron Hernandez"},{"NombreProyecto":"IRV - Retail QA","NombreLider":"Ernesto Anaya"},{"NombreProyecto":"IRV - Safety Management Mobile App","NombreLider":"Guillermo Cantu"},{"NombreProyecto":"IRV - Sublease","NombreLider":"Guillermo Cantu"},{"NombreProyecto":"IRV - Sublease","NombreLider":"Pivotal Retirement"},{"NombreProyecto":"IRV - Sublease","NombreLider":"Pivotal Retirement"},{"NombreProyecto":"IRV - Sublease","NombreLider":"Pivotal Retirement"},{"NombreProyecto":"IRV - Support","NombreLider":"Guillermo Cantu"},{"NombreProyecto":"Pivotal Retirement","NombreLider":"Guillermo Cantu"},{"NombreProyecto":"JMT -  MVP Jammin' Together","NombreLider":"Pablo Nuñez"},{"NombreProyecto":"SCL -  Mobile & Desktop Design","NombreLider":"Irasema Fernandez"},{"NombreProyecto":"SCL - Web App Redesign","NombreLider":"Raul Nunez"},{"NombreProyecto":"SFT - Knowledge Transfer and Documentation","NombreLider":"Eduardo Muñoz"},{"NombreProyecto":"SFT - Support and New Features","NombreLider":"Eduardo Muñoz"},{"NombreProyecto":"SFT - Support and New Features","NombreLider":"Jara Diaz de Leon , Erendira Citlalli"},{"NombreProyecto":"SWR - Online Booking Widget","NombreLider":"Lauro Bolado"},{"NombreProyecto":"TCA - IQ updates and fixes","NombreLider":"Raul Aguilera"},{"NombreProyecto":"TXL - Traxxall Mobile","NombreLider":"Alejandro Garcia"},{"NombreProyecto":"WLD - OLA","NombreLider":"Pablo Nuñez"},{"NombreProyecto":"WLD - Tempo","NombreLider":"Eduardo Muñoz"},{"NombreProyecto":"WLD - Walden Website","NombreLider":"Eduardo Muñoz"}]